CHANGES.rst
CONTRIBUTORS.rst
DEVELOP.rst
LICENSE.GPL
LICENSE.rst
MANIFEST.in
README.rst
requirements.txt
setup.cfg
setup.py
docs/index.rst
src/collective/__init__.py
src/collective.easyformplugin.registration.egg-info/PKG-INFO
src/collective.easyformplugin.registration.egg-info/SOURCES.txt
src/collective.easyformplugin.registration.egg-info/dependency_links.txt
src/collective.easyformplugin.registration.egg-info/entry_points.txt
src/collective.easyformplugin.registration.egg-info/namespace_packages.txt
src/collective.easyformplugin.registration.egg-info/not-zip-safe
src/collective.easyformplugin.registration.egg-info/requires.txt
src/collective.easyformplugin.registration.egg-info/top_level.txt
src/collective/easyformplugin/__init__.py
src/collective/easyformplugin/registration/__init__.py
src/collective/easyformplugin/registration/actions.py
src/collective/easyformplugin/registration/actions.zcml
src/collective/easyformplugin/registration/behavior.py
src/collective/easyformplugin/registration/configure.zcml
src/collective/easyformplugin/registration/event.py
src/collective/easyformplugin/registration/interfaces.py
src/collective/easyformplugin/registration/registration_action_model.xml
src/collective/easyformplugin/registration/setuphandlers.py
src/collective/easyformplugin/registration/testing.py
src/collective/easyformplugin/registration/upgrades.py
src/collective/easyformplugin/registration/upgrades.zcml
src/collective/easyformplugin/registration/vocabularies.py
src/collective/easyformplugin/registration/browser/__init__.py
src/collective/easyformplugin/registration/browser/configure.zcml
src/collective/easyformplugin/registration/browser/contact-registrants-email.pt
src/collective/easyformplugin/registration/browser/contact_registrants_view.pt
src/collective/easyformplugin/registration/browser/contact_registrants_view.py
src/collective/easyformplugin/registration/browser/registration_form.pt
src/collective/easyformplugin/registration/browser/view.py
src/collective/easyformplugin/registration/browser/static/.gitkeep
src/collective/easyformplugin/registration/browser/static/contact_registrants.js
src/collective/easyformplugin/registration/default_schemata/actions_default.xml
src/collective/easyformplugin/registration/default_schemata/fields_default.xml
src/collective/easyformplugin/registration/locales/README.rst
src/collective/easyformplugin/registration/locales/__init__.py
src/collective/easyformplugin/registration/locales/collective.easyformplugin.registration.pot
