Metadata-Version: 2.1
Name: collective.easyformplugin.registration
Version: 2.0.0
Summary: Add a behavior to collective.easyform to manage registration forms
Home-page: https://github.com/collective/collective.easyformplugin.registration
Author: Andrea Cecchi
Author-email: andrea.cecchi85@gmail.com
License: GPL version 2
Keywords: Python Plone
Platform: UNKNOWN
Classifier: Environment :: Web Environment
Classifier: Framework :: Plone
Classifier: Framework :: Plone :: 5.2
Classifier: Framework :: Plone :: 6.0
Classifier: Programming Language :: Python
Classifier: Programming Language :: Python :: 3.6
Classifier: Programming Language :: Python :: 3.7
Classifier: Programming Language :: Python :: 3.8
Classifier: Operating System :: OS Independent
Classifier: License :: OSI Approved :: GNU General Public License v2 (GPLv2)
Provides-Extra: test
